Workbook

Sheet Backlog
A1: Task ID | B1: Theme (Epic) | C1: Capability (Feature) | D1: Sub-capability (Story) | E1: Task | F1: Description | G1: Acceptance criteria | H1: Size | I1: Priority | J1: Dependencies | K1: Owner role | L1: Phase | M1: Status
A2: FND-001 | B2: Foundation & ABC Modernization | C2: Metadata/Config Model | D2: Define config model | E2: Spec: author metadata/config model (.md) | F2: Define config entities: source, target, load, transform, DQ rule, recon rule, masking rule, dependency. | G2: Spec reviewed and approved; covers all framework config objects and ABC linkage. | H2: M | I2: Must | J2: - | K2: Architect | L2: Foundation | M2: Not Started
A3: FND-002 | B3: Foundation & ABC Modernization | C3: Metadata/Config Model | D3: Define config model | E3: Design Delta control tables (DDL) | F3: Physical control tables for the config registry and their relationship to existing ABC tables. | G3: DDL created in Unity Catalog; FKs/keys defined; aligns with ABC schema. | H3: M | I3: Must | J3: FND-001 | K3: Data Engineer | L3: Foundation | M3: Not Started
A4: FND-003 | B4: Foundation & ABC Modernization | C4: Metadata/Config Model | D4: Config runtime | E4: Implement config loader + validator | F4: Typed config loader with schema validation and helpful errors. | G4: Loads sample config; rejects invalid config with clear messages; unit-tested. | H4: M | I4: Must | J4: FND-002 | K4: Data Engineer | L4: Foundation | M4: Not Started
A5: FND-004 | B5: Foundation & ABC Modernization | C5: Metadata/Config Model | D5: Config runtime | E5: Seed example P&C configs | F5: Example configs for one policy feed and one harmonization transform. | G5: Configs load and drive a sample run end to end. | H5: S | I5: Should | J5: FND-003 | K5: Data Engineer | L5: Foundation | M5: Not Started
A6: FND-005 | B6: Foundation & ABC Modernization | C6: Metadata/Config Model | D6: Config governance | E6: Config versioning + change audit | F6: Version metadata changes and record who/when/what to ABC. | G6: Edits are versioned; change history queryable in ABC. | H6: M | I6: Should | J6: FND-002 | K6: Data Engineer | L6: Foundation | M6: Not Started
A7: FND-010 | B7: Foundation & ABC Modernization | C7: ABC SDK | D7: ABC interface | E7: Spec: ABC SDK interface (.md) | F7: Define start_run/end_run/log_balance/log_dq/log_exception/log_cost contract. | G7: Interface signed off; mapped to existing ABC tables. | H7: S | I7: Must | J7: FND-001 | K7: Architect | L7: Foundation | M7: Not Started
A8: FND-011 | B8: Foundation & ABC Modernization | C8: ABC SDK | D8: ABC interface | E8: Implement ABC SDK (workspace Python modules) | F8: Reusable SDK wrapping existing ABC Delta tables; replaces direct table writes. | G8: SDK delivered as workspace Python modules; writes verified against ABC tables. | H8: L | I8: Must | J8: FND-010 | K8: Data Engineer | L8: Foundation | M8: Not Started
A9: FND-012 | B9: Foundation & ABC Modernization | C9: ABC SDK | D9: Notebook modernization | E9: Migrate existing ABC notebooks to SDK | F9: Refactor current ABC-interfacing notebooks to call the SDK (real environment). | G9: Notebooks use SDK; behavior parity with current ABC logging. | H9: L | I9: Must | J9: FND-011 | K9: Data Engineer | L9: Build (Paid) | M9: Not Started
A10: FND-013 | B10: Foundation & ABC Modernization | C10: ABC SDK | D10: Quality | E10: Unit tests for ABC SDK | F10: Cover run lifecycle, balance, DQ, exception, cost logging. | G10: Coverage > 80% on SDK; tests pass in CI. | H10: M | I10: Must | J10: FND-011 | K10: QA | L10: Foundation | M10: Not Started
A11: FND-014 | B11: Foundation & ABC Modernization | C11: ABC SDK | D11: Quality | E11: Backward-compat check vs ABC schema | F11: Confirm SDK writes match existing ABC schema/consumers. | G11: No breaking change to existing ABC consumers. | H11: S | I11: Must | J11: FND-011 | K11: Data Engineer | L11: Foundation | M11: Not Started
A12: FND-020 | B12: Foundation & ABC Modernization | C12: Core Control Skills | D12: Self-governance | E12: Self-Review skill | F12: Agent validates generated artifacts against standards before submitting. | G12: Generated artifacts pass a standards checklist; violations flagged. | H12: M | I12: Should | J12: FND-010 | K12: ML/AI Engineer | L12: Build (Paid) | M12: Not Started
... A116: ENABLE-011 | B116: Specs & Documentation | C116: Docs | D116: Demo | E116: PoC demo script + walkthrough | F116: Narrative and steps to demo the PoC slice. | G116: Demo script runs cleanly end to end. | H116: S | I116: Could | J116: BENCH-010 | K116: Tech Writer | L116: Enablement | M116: Not Started

Sheet Legend
A1: Legend & Conventions
A3: Columns | B3: Meaning
A4: Task ID | B4: Unique ID, prefixed by component (FND, ING, HARM, DQ, REC, MASK, AGENT, FINOPS, OBS, DEVOPS, BENCH, ENABLE).
A5: Theme (Epic) | B5: Top-level workstream / framework.
A6: Capability (Feature) | B6: Feature group within the epic.
A7: Sub-capability (Story) | B7: Story-level grouping of tasks.
A8: Task | B8: Low-level, actionable unit of work (~0.5-2 days).
A9: Description | B9: What the task delivers.
A10: Acceptance criteria | B10: Definition of Done for the task.
A11: Size | B11: T-shirt estimate (see sizing key).
A12: Priority | B12: MoSCoW priority.
A13: Dependencies | B13: Predecessor Task IDs (comma-separated).
A14: Owner role | B14: Suggested role; names left blank to assign.
... A35: Enablement | B35: Documentation, demo and runbooks.
A37: Notes
A38: Specs (.md) are the portable IP: authored in Claude Cowork, used to benchmark on Free Edition, then reused to build on the paid workspace.
A39: Free Edition limits: serverless only, one active pipeline per type, 5 concurrent job tasks, one 2X-Small SQL warehouse, limited model serving, restricted outbound internet, daily quotas.
A40: On Free Edition use synthetic data (no live CDC); heavier agentic/serving tasks are 'Build (Paid)'.
A41: FinOps: measure consumption on Free Edition, apply paid list prices (post-6-Jul-2026 Genie pricing), scale by volume = probable customer cost.

Sheet Summary
A1: Backlog Summary
A3: Total tasks | B3: =COUNTA(Backlog!$A$2:$A$116) -> 115
A5: By Epic | B5: Count
A6: Foundation & ABC Modernization | B6: =COUNTIF(Backlog!$B$2:$B$116,A6) -> 17
A7: Ingestion Framework | B7: =COUNTIF(Backlog!$B$2:$B$116,A7) -> 15
A8: Harmonization / Curation Framework | B8: =COUNTIF(Backlog!$B$2:$B$116,A8) -> 16
A9: Data Quality Framework | B9: =COUNTIF(Backlog!$B$2:$B$116,A9) -> 9
A10: Reconciliation Framework | B10: =COUNTIF(Backlog!$B$2:$B$116,A10) -> 7
A11: Data Masking | B11: =COUNTIF(Backlog!$B$2:$B$116,A11) -> 6
A12: Agentic Solution | B12: =COUNTIF(Backlog!$B$2:$B$116,A12) -> 19
A13: FinOps & Cost Management | B13: =COUNTIF(Backlog!$B$2:$B$116,A13) -> 8
A14: Observability | B14: =COUNTIF(Backlog!$B$2:$B$116,A14) -> 4
A15: CI/CD & DevOps | B15: =COUNTIF(Backlog!$B$2:$B$116,A15) -> 5
A16: PoC Benchmark Harness | B16: =COUNTIF(Backlog!$B$2:$B$116,A16) -> 6
A17: Specs & Documentation | B17: =COUNTIF(Backlog!$B$2:$B$116,A17) -> 3
A19: By Phase | B19: Count
A20: Foundation | B20: =COUNTIF(Backlog!$L$2:$L$116,A20) -> 26
A21: PoC-Benchmark (Free) | B21: =COUNTIF(Backlog!$L$2:$L$116,A21) -> 7
A22: Build (Paid) | B22: =COUNTIF(Backlog!$L$2:$L$116,A22) -> 78
A23: Hardening (Paid) | B23: =COUNTIF(Backlog!$L$2:$L$116,A23) -> 2
A24: Enablement | B24: =COUNTIF(Backlog!$L$2:$L$116,A24) -> 2
A26: By Size | B26: Count
A27: S | B27: =COUNTIF(Backlog!$H$2:$H$116,A27) -> 25
A28: M | B28: =COUNTIF(Backlog!$H$2:$H$116,A28) -> 72
A29: L | B29: =COUNTIF(Backlog!$H$2:$H$116,A29) -> 17
A30: XL | B30: =COUNTIF(Backlog!$H$2:$H$116,A30) -> 1
A32: By Priority | B32: Count
A33: Must | B33: =COUNTIF(Backlog!$I$2:$I$116,A33) -> 72
A34: Should | B34: =COUNTIF(Backlog!$I$2:$I$116,A34) -> 31
A35: Could | B35: =COUNTIF(Backlog!$I$2:$I$116,A35) -> 12
A36: Won't | B36: =COUNTIF(Backlog!$I$2:$I$116,A36) -> 0
